{
  "id": "mac",
  "source": "Advanced Mac Admin",
  "sections": [
    {
      "title": "Section 7: Advanced Mac Management",
      "items": [
        {
          "id": "mac-1",
          "question": "Should we still bind our Macs to Active Directory (AD)? What is the modern recommendation?",
          "answer": "<p><strong>We strongly recommend a “No-Bind” strategy. Instead of traditional AD binding, schools should adopt Platform SSO or Jamf Connect.</strong></p>\n<p>The traditional method of “Binding” a Mac to a Domain Controller (DC) is increasingly unreliable in a modern campus environment characterized by mobile laptops and Zero Trust security.</p>\n<h2>Why Move Away from AD Binding?</h2>\n<ol>\n<li><strong>Mobility Barriers</strong>: If a teacher takes their MacBook home, they are disconnected from the DC. This often causes slow logins or failures when trying to sync password changes made on campus.</li>\n<li><strong>Keychain Synchronization Issues</strong>: When an AD password is changed, the local Mac “Keychain” often falls out of sync, leading to constant and frustrating password prompts for the user.</li>\n<li><strong>Legacy Technology</strong>: Apple is no longer actively developing the AD Plugin. Modern macOS management is built around Cloud Identity Providers (IdP).</li>\n</ol>\n<h2>Modern Alternatives for 2026:</h2>\n<h3>Option A: Platform SSO 2.0 (The Standard for macOS 26 Tahoe)</h3>\n<p>Introduced in macOS 13 and fully matured in <strong>macOS 26</strong>, Platform SSO is the Apple-native way to link your Cloud ID (Google, Microsoft Entra ID) to the local Mac login.</p>\n<ul>\n<li>\n<p><strong>Simplified Setup</strong>: During the out-of-box “Setup Assistant,” the Mac requires the student to log in with their campus ID, which then automatically creates their local account.</p>\n</li>\n<li>\n<p><strong>Seamless Sync</strong>: The local Mac password is kept perfectly in sync with the cloud password.</p>\n</li>\n<li>\n<p><strong>Passwordless Future</strong>: macOS 26 supports authorized logins using Face ID or Touch ID, significantly reducing “forgotten password” tickets.</p>\n</li>\n</ul>\n<h3>Option B: Jamf Connect</h3>\n<p>For schools requiring more granular control or custom branding (e.g., displaying the school logo and Acceptable Use Policy on the login screen).</p>\n<ul>\n<li>\n<p><strong>Just-in-Time Provisioning</strong>: It creates the local account the first time a user logs in with their cloud credentials.</p>\n</li>\n<li>\n<p><strong>Enforced Multi-Factor Authentication (MFA)</strong>: You can require students or staff to pass an MFA check (phone app or security key) before they can even reach the Mac desktop.</p>\n</li>\n</ul>\n<h2>Institutional Advice:</h2>\n<p>If your school still has a large fleet of AD-bound Macs, we recommend a phased “Unbind” project. Migrating to <strong>Platform SSO</strong> will drastically reduce the support burden associated with “Password Desynchronization” and login delays.</p>\n",
          "important": true,
          "tags": ["AD", "Identity", "Jamf Connect", "Platform SSO", "No-Bind"],
          "category": "Section 7: Advanced Mac Management"
        },
        {
          "id": "mac-2",
          "question": "How do we manage Local Admin privileges for staff and students on Macs?",
          "answer": "<p><strong>The Gold Standard is to provide “Standard User” accounts for daily tasks, supplemented by a “just-in-time” Admin elevation tool or a Managed LAPS solution.</strong></p>\n<p>Granting permanent Admin rights to students or teachers is a major security risk. It allows for the disabling of security software, the installation of unauthorized apps, and makes the campus network more vulnerable to ransomware.</p>\n<h2>The Three-Tier Management Strategy:</h2>\n<h3>1. Standard User by Default</h3>\n<ul>\n<li>All school-issued Macs should be set up with “Standard User” accounts. This prevents users from altering core system settings or installing system-wide software without oversight.</li>\n</ul>\n<h3>2. Native LAPS (Local Administrator Password Solution)</h3>\n<ul>\n<li><strong>2026 Status</strong>: As of <strong>macOS 26</strong>, Apple includes a native LAPS protocol.</li>\n<li><strong>How it works</strong>: Jamf Pro creates a hidden admin account on every Mac. The password for this account is a long, random string that <strong>rotates automatically</strong> every few days.</li>\n<li><strong>Operational use</strong>: If a technician needs to fix a Mac, they look up the <em>current</em> random password in the Jamf dashboard. Once used, the password is refreshed, ensuring the old one can never be used again.</li>\n</ul>\n<h3>3. Self-Service Elevation (Privileges App)</h3>\n<p>For staff members who occasionally need to install a printer driver or specialized software:</p>\n<ul>\n<li>\n<p><strong>Tool</strong>: Deploy the <strong>Privileges</strong> app (or Jamf’s equivalent).</p>\n</li>\n<li>\n<p><strong>Workflow</strong>: The teacher clicks a lock icon in the Dock, justifies the need, and is granted <strong>Admin rights for 20 minutes</strong>. After the timer expires, the system automatically demotes them back to a Standard User.</p>\n</li>\n</ul>\n<h2>Institutional Advice:</h2>\n<p>Adopting the “Principle of Least Privilege” does not mean making life difficult for teachers; it means providing them with the tools to be productive while ensuring the school’s digital assets remain secure and compliant with insurance standards.</p>\n",
          "important": false,
          "tags": ["Privilege Management", "LAPS", "Security", "Standard User"],
          "category": "Section 7: Advanced Mac Management"
        },
        {
          "id": "mac-3",
          "question": "How do we distribute non-App Store software like Chrome, Adobe CC, or Office?",
          "answer": "<p><strong>Move away from manual packaging. Use Jamf Pro’s “App Installers” for high-frequency apps, and DDM-based distribution for mission-critical software.</strong></p>\n<p>Managing Mac software used to involve a tedious cycle of downloading DMGs, repackaging them into PKGs, and uploading them. Today, there are much more efficient pathways.</p>\n<h2>Modern Software Deployment Tiers:</h2>\n<h3>Tier 1: Jamf App Installers (Preferred)</h3>\n<ul>\n<li><strong>The Workflow</strong>: You choose “Google Chrome” from the Jamf catalog. Jamf handles the downloading, packaging, and—crucially—the <strong>Automatic Updates</strong>.</li>\n<li><strong>Self-Healing</strong>: In <strong>macOS 26</strong>, this is backed by DDM. If a student deletes Chrome, the Mac notices the “State Desync” and automatically reinstalls the app in the background without any IT intervention.</li>\n</ul>\n<h3>Tier 2: Mac App Store (VPP)</h3>\n<ul>\n<li>Best for classroom favorites like Goodnotes, Keynote, or GarageBand.</li>\n<li>Purchase licenses in bulk via Apple School Manager and push them to devices. Installation is silent and updates are managed by the system.</li>\n</ul>\n<h3>Tier 3: Adobe Creative Cloud (Shared Device License)</h3>\n<ul>\n<li>For computer labs, use the <strong>Adobe Admin Console</strong> to create a “Shared Device License” package.</li>\n<li>Push this package via a Jamf Pro policy. This ensures that any student who sits at the Mac can use the software using their individual school ID.</li>\n</ul>\n<h3>Tier 4: Custom PKGs (Last Resort)</h3>\n<ul>\n<li>Use <strong>Jamf Composer</strong> to package specialized local curriculum software or niche drivers that are not found in public catalogs.</li>\n</ul>\n<h2>Institutional Advice:</h2>\n<p>Focus on the “App Installers” catalog for 90% of your needs. Ensuring that apps like Chrome and Zoom are automatically kept on the latest version is the single best way to reduce security vulnerabilities across the campus.</p>\n",
          "important": false,
          "tags": [
            "Software Distribution",
            "App Installers",
            "PKG",
            "Auto-Update"
          ],
          "category": "Section 7: Advanced Mac Management"
        },
        {
          "id": "mac-4",
          "question": "How should we design our macOS update strategy for 2026? How does DDM change things?",
          "answer": "<p><strong>In the macOS 26 (Tahoe) era, Apple has fully transitioned to Declarative Device Management (DDM) for software updates. IT teams no longer “send a command” to update; they “declare a state.”</strong></p>\n<p>This shift solves the old problem of update commands being ignored or failing due to network timing.</p>\n<h2>I. Traditional vs. Declarative (DDM) Updates</h2>\n<table>\n<thead>\n<tr>\n<th style=\"text-align:left\">Feature</th>\n<th style=\"text-align:left\">Old MDM Command</th>\n<th style=\"text-align:left\">New DDM (macOS 23+)</th>\n</tr>\n</thead>\n<tbody>\n<tr>\n<td style=\"text-align:left\"><strong>Logic</strong></td>\n<td style=\"text-align:left\">Server pushes, Device might ignore</td>\n<td style=\"text-align:left\"><strong>Device self-monitors</strong> and enforces</td>\n</tr>\n<tr>\n<td style=\"text-align:left\"><strong>Deadlines</strong></td>\n<td style=\"text-align:left\">Optional / Flaky</td>\n<td style=\"text-align:left\"><strong>Hard Enforcement Deadlines</strong></td>\n</tr>\n<tr>\n<td style=\"text-align:left\"><strong>User Experience</strong></td>\n<td style=\"text-align:left\">Random popups</td>\n<td style=\"text-align:left\">Clear countdowns and notifications</td>\n</tr>\n<tr>\n<td style=\"text-align:left\"><strong>Visibility</strong></td>\n<td style=\"text-align:left\">“Unknown” status until done</td>\n<td style=\"text-align:left\">Real-time status: “Downloading,” “Ready”</td>\n</tr>\n</tbody>\n</table>\n<h2>II. 2026 Standard Operating Procedure for IT</h2>\n<h3>1. Set Enforcement Deadlines</h3>\n<ul>\n<li><strong>Major Updates (e.g., 26.1)</strong>: Set a deadline for <strong>14-21 days</strong> after release. This gives everyone time to choose a convenient moment.</li>\n<li><strong>Security Patches (RSR)</strong>: Set a deadline for <strong>48 hours</strong>. Critical security shouldn’t wait.</li>\n<li><strong>The Result</strong>: Users get multiple gentle reminders. If they haven’t updated by the deadline, the Mac will <strong>force a restart and install</strong> automatically at the specified time.</li>\n</ul>\n<h3>2. Utilize DDM Status Channels</h3>\n<ul>\n<li>Administrators no longer need to manually “Scan for Inventory” to see who is updated.</li>\n<li>DDM actively reports its progress: “I have downloaded the update and scheduled installation for 17:00.”</li>\n</ul>\n<h3>3. Campus Network Infrastructure</h3>\n<ul>\n<li>Massive simultaneous DDM updates place extreme stress on school bandwidth.</li>\n<li><strong>Key Infrastructure</strong>: Ensure each administrative or classroom building has at least one Mac mini acting as a <strong>“Content Caching”</strong> server. This ensures 90% of the update traffic stays on the local network.</li>\n</ul>\n<h2>III. Practical Reminders</h2>\n<ul>\n<li><strong>Avoid Exam Weeks</strong>: DDM enforcement is highly strictly. During assessment weeks or high-stakes exams, please temporarily unassign the update profile to prevent a student’s Mac from automatically restarting mid-exam because a deadline was reached.</li>\n</ul>\n<h2>Institutional Advice:</h2>\n<p>Transitioning to DDM Enforcement Deadlines is the only way to ensure 100% compliance across a laptop fleet. It moves the responsibility of “staying updated” from the student to the hardware itself.</p>\n",
          "important": true,
          "tags": [
            "Software Updates",
            "DDM",
            "macOS 26",
            "Compliance",
            "IT Strategy"
          ],
          "category": "Section 7: Advanced Mac Management"
        },
        {
          "id": "mac-5",
          "question": "How do I force a Mac to perform system updates? Students keep clicking 'Remind Me Later'.",
          "answer": "<p><strong>The modern solution is to use “Declarative Device Management (DDM).”</strong> If you need more visual urgency, you can supplement this with the open-source tool “Nudge.”</p>\n<p>Unlike iPads, Mac updates often require a lengthy restart, which leads students to postpone them indefinitely, creating a fragmented and insecure fleet.</p>\n<h2>Strategy 1: DDM Enforced Updates (Recommended for macOS 14+)</h2>\n<ul>\n<li>\n<p><strong>The Logic</strong>: This is Apple’s newest management protocol. IT administrators set an <strong>“Enforcement Deadline.”</strong></p>\n</li>\n<li>\n<p><strong>The Workflow</strong>:</p>\n<ol>\n<li>In the days leading up to the deadline, the system gently notifies the student.</li>\n<li>As the deadline approaches, the notifications become more persistent.</li>\n<li><strong>Once the deadline is reached</strong>, the Mac will automatically download the update and force a restart. The student cannot postpone it further.</li>\n</ol>\n</li>\n<li>\n<p><strong>Configuration</strong>: This is set in Jamf Pro under <strong>Configuration Profiles &gt; Software Update</strong>, where you define the target version and the specific cut-off date and time.</p>\n</li>\n</ul>\n<h2>Strategy 2: Nudge (Visual Urgency)</h2>\n<p>If the subtle system notifications aren’t enough, the community-standard tool <strong>Nudge</strong> is the best solution.</p>\n<ul>\n<li>\n<p><strong>Functionality</strong>: It pops up a non-dismissible window (which can be branded with the school logo) that clearly states: “Your Mac is out of date and insecure. Please update now.”</p>\n</li>\n<li>\n<p><strong>Escalation</strong>: As the deadline nears, Nudge can dim the screen or blur the background, making it impossible for the student to ignore the update while they try to use other apps.</p>\n</li>\n<li>\n<p><strong>Deployment</strong>: Deploy the Nudge package and JSON configuration via Jamf Pro.</p>\n</li>\n</ul>\n<h2>Institutional Advice:</h2>\n<p>For computer labs that are unoccupied at night, use Jamf Pro to schedule a “Wake Up” command at 2:00 AM followed by a “Force Update” command. This allows the heavy lifting to happen while the students are asleep, ensuring the labs are ready and updated for the first period.</p>\n",
          "important": false,
          "tags": ["System Updates", "DDM", "Nudge", "IT Operations"],
          "category": "Section 7: Advanced Mac Management"
        },
        {
          "id": "mac-6",
          "question": "How can I quickly reset (wipe) a Mac lab, similar to using recovery cards?",
          "answer": "<p><strong>In the era of Apple Silicon (M-series), using “recovery cards” or “Ghost” imaging is no longer recommended and often not even possible. Instead, use the “Erase All Content and Settings (EACS)” command.</strong></p>\n<p>Traditional monolithic imaging has been completely retired by Apple. The modern reset logic is “Clear user data + Keep operating system + Automatically re-enroll.”</p>\n<h2>Comparison of Reset Methods</h2>\n<table>\n<thead>\n<tr>\n<th style=\"text-align:left\">Feature</th>\n<th style=\"text-align:left\">Legacy Re-imaging</th>\n<th style=\"text-align:left\">Erase All Content and Settings (EACS)</th>\n</tr>\n</thead>\n<tbody>\n<tr>\n<td style=\"text-align:left\"><strong>Principle</strong></td>\n<td style=\"text-align:left\">Format drive &gt; Re-download &amp; install OS</td>\n<td style=\"text-align:left\">Destroy encryption keys &gt; Clear user data</td>\n</tr>\n<tr>\n<td style=\"text-align:left\"><strong>Time Required</strong></td>\n<td style=\"text-align:left\">1-2 hours</td>\n<td style=\"text-align:left\"><strong>5-10 minutes</strong></td>\n</tr>\n<tr>\n<td style=\"text-align:left\"><strong>Network Demand</strong></td>\n<td style=\"text-align:left\">Requires 12GB+ OS download</td>\n<td style=\"text-align:left\"><strong>Minimal bandwidth</strong></td>\n</tr>\n<tr>\n<td style=\"text-align:left\"><strong>Data Security</strong></td>\n<td style=\"text-align:left\">Disk formatting (recoverable)</td>\n<td style=\"text-align:left\">Cryptographic destruction (unrecoverable)</td>\n</tr>\n<tr>\n<td style=\"text-align:left\"><strong>Hardware Support</strong></td>\n<td style=\"text-align:left\">All Intel/Apple Silicon Macs</td>\n<td style=\"text-align:left\">Macs with T2 or Apple Silicon chips</td>\n</tr>\n</tbody>\n</table>\n<h2>Standard Reset SOP (Jamf Pro)</h2>\n<h3>1. Send Command</h3>\n<ul>\n<li>Send the <strong>“Wipe Computer”</strong> command to the target computer group in Jamf Pro.</li>\n<li><strong>Crucial</strong>: For Apple Silicon and T2-equipped Macs, this command automatically triggers <strong>EACS (Erase All Content and Settings)</strong>.</li>\n</ul>\n<h3>2. Execution (Within minutes)</h3>\n<ul>\n<li>The system instantly discards the encryption keys (Cryptographic Erase), making data unreadable within seconds.</li>\n<li>The computer reboots to the “Hello” (Setup Assistant) screen.</li>\n</ul>\n<h3>3. Automated Deployment (Zero-Touch)</h3>\n<ul>\n<li>The computer connects to the network (Ensure a non-authenticated Wi-Fi or wired network is provided).</li>\n<li><strong>ADE (Automated Device Enrollment)</strong> is triggered automatically.</li>\n<li>PreStage Enrollment settings are downloaded, admin accounts are created, and software is installed automatically.</li>\n</ul>\n<h2>Difference from Traditional Recovery Cards</h2>\n<ul>\n<li>Traditional cards “restore on every reboot.”</li>\n<li>Modern Mac management uses EACS reset at the “end of a semester or project.”</li>\n<li>If daily restoration is required (e.g., for library public kiosks), consider using <strong>“Guest User” mode</strong> (which deletes data upon logout) or specialized kiosk software (like Deep Freeze for Mac).</li>\n</ul>\n",
          "important": false,
          "tags": [
            "Reset",
            "EACS",
            "Erase All Content and Settings",
            "Computer Lab",
            "Imaging"
          ],
          "category": "Section 7: Advanced Mac Management"
        },
        {
          "id": "mac-7",
          "question": "What special restrictions apply to managing Apple Silicon (M-series) Macs?",
          "answer": "<p><strong>The security architecture of Apple Silicon (M1-M5) is fundamentally different from Intel Macs. The core of management lies in the “Bootstrap Token” and “Volume Ownership.”</strong></p>\n<p>Without proper configuration, MDM will be unable to perform software updates or install kernel plugins.</p>\n<h2>Key Technical Indicators:</h2>\n<h3>1. Bootstrap Token</h3>\n<ul>\n<li><strong>The Issue</strong>: On Apple Silicon, certain high-privilege operations (such as installing software updates or enabling kernel extensions) require a “Secure Token.”</li>\n<li><strong>The Solution</strong>: Ensure that <strong>“Allow MDM to upload Bootstrap Token”</strong> is checked in the Jamf Pro <strong>PreStage Enrollment</strong> settings.</li>\n<li><strong>Verification</strong>: In the Jamf Pro computer record, confirm that <code>Bootstrap Token Allowed</code> is set to <code>Yes</code>. If it is “No,” many management commands will fail.</li>\n</ul>\n<h3>2. Volume Ownership</h3>\n<ul>\n<li>Only users designated as “Owners” can perform system resets or updates.</li>\n<li>The first account created through ADE enrollment automatically gains ownership. MDM escorts this privilege via the Bootstrap Token.</li>\n</ul>\n<h3>3. Kernel Extensions (KEXTs)</h3>\n<ul>\n<li>Apple Silicon <strong>blocks</strong> all third-party KEXTs by default.</li>\n<li>If they must be installed (e.g., for older antivirus software), the device must be rebooted into Recovery Mode to lower the security setting to “Reduced Security.”</li>\n<li><strong>Modern Recommendation</strong>: Use <strong>System Extensions</strong> instead. This is Apple’s recommended architecture, which can be authorized directly via MDM configuration profiles without lowering system security.</li>\n</ul>\n",
          "important": false,
          "tags": [
            "Apple Silicon",
            "Bootstrap Token",
            "Secure Boot",
            "Kernel Extensions"
          ],
          "category": "Section 7: Advanced Mac Management"
        },
        {
          "id": "mac-8",
          "question": "Why does MDM require FileVault? How do I recover a forgotten login password?",
          "answer": "<p><strong>FileVault is macOS’s built-in “Full Disk Encryption” technology, ensuring that data cannot be stolen if the computer is lost. By escrowing the “Recovery Key” to MDM, administrators can help unlock the device if a user forgets their password.</strong></p>\n<h2>Technical Principles:</h2>\n<ul>\n<li><strong>XTS-AES-128 Encryption</strong>: Before login, the hard drive data is encrypted and unreadable.</li>\n<li><strong>Performance Impact</strong>: Modern Macs handle encryption via the Secure Enclave hardware, resulting in virtually zero impact on daily performance.</li>\n<li><strong>2026 Experience: Platform SSO (PSSO)</strong>: In macOS 26, using PSSO allows users to enter their password just once at the FileVault screen to boot directly to the desktop. The system automatically handles subsequent identity provider (IdP) verification and login. This eliminates the legacy “double login” frustration.</li>\n</ul>\n<h2>Jamf Pro Deployment and Escrow Flow (SOP):</h2>\n<h3>1. Create Configuration Profile</h3>\n<ul>\n<li>Go to <strong>Configuration Profiles &gt; New &gt; FileVault</strong>.</li>\n<li>Set to <strong>Require FileVault</strong>.</li>\n<li><strong>Crucial Step</strong>: Set to <strong>Create Personal Recovery Key</strong> and choose <strong>Escrow Personal Recovery Key to MDM</strong>.</li>\n</ul>\n<h3>2. User-Side Activation</h3>\n<ul>\n<li>After deployment, the system will prompt the user to enable encryption at the next logout or reboot.</li>\n<li><strong>Note</strong>: Jamf Pro will only receive the key once the user completes this step and the status changes to “Encrypted.”</li>\n</ul>\n<h2>Recovery Scenario: Looking up the Recovery Key</h2>\n<p>If a user forgets their password, the administrator must retrieve the key from the console.</p>\n<h3>1. Navigate to Inventory</h3>\n<ul>\n<li>Log in to Jamf Pro and search for the target computer.</li>\n<li>Go to the detail page and select the <strong>Inventory</strong> tab &gt; <strong>Disk Encryption</strong>.</li>\n</ul>\n<h3>2. Verify Encryption and Key</h3>\n<ul>\n<li>First, check if <strong>FileVault 2 Enabled</strong> is set to <strong>Encrypted</strong> or <strong>Enabled</strong>.</li>\n<li><strong>If Encrypted</strong>: You will see a <strong>Personal Recovery Key</strong> field. Click <strong>Show Key</strong> to reveal the code.</li>\n<li><strong>If Not Encrypted</strong>: This field will not appear, meaning encryption is incomplete or the escrow failed. Recovery via MDM is not possible in this state.</li>\n</ul>\n<h3>3. Perform the Unlock</h3>\n<ul>\n<li>On the Mac login screen, click the question mark (?) or enter the wrong password three times. Select <strong>Reset password using Recovery Key</strong> and enter the code.</li>\n</ul>\n<h2>Practical Advice &amp; Warnings:</h2>\n<ul>\n<li><strong>Data Loss Risk</strong>: If FileVault is enabled but Jamf Pro shows “Unknown” or no key, the escrow failed. If the password is forgotten in this state, <strong>data is permanently unrecoverable</strong>, and the device must be wiped.</li>\n<li><strong>Institutional Recovery Key (IRK)</strong>: Modern management favors the “Personal Recovery Key (PRK)” mechanism for higher security.</li>\n</ul>\n",
          "important": true,
          "tags": [
            "FileVault",
            "Full Disk Encryption",
            "Data Security",
            "Recovery Key",
            "Jamf Pro",
            "Inventory"
          ],
          "category": "Section 7: Advanced Mac Management"
        },
        {
          "id": "mac-9",
          "question": "What can Jamf Scripts do? How do I create and run them?",
          "answer": "<p><strong>Scripts allow administrators to execute shell commands with Root privileges on a Mac, enabling advanced customization that standard MDM payloads cannot achieve.</strong></p>\n<p>Jamf Pro’s power lies in its proprietary binary. When combined with <strong>Policies</strong>, you can achieve the following advanced scenarios:</p>\n<h2>Common Application Scenarios:</h2>\n<table>\n<thead>\n<tr>\n<th style=\"text-align:left\">Scenario</th>\n<th style=\"text-align:left\">Script Example</th>\n</tr>\n</thead>\n<tbody>\n<tr>\n<td style=\"text-align:left\"><strong>User Interaction</strong></td>\n<td style=\"text-align:left\">Use <code>jamfHelper</code> to pop up full-screen announcements or countdown windows.</td>\n</tr>\n<tr>\n<td style=\"text-align:left\"><strong>System Cleanup</strong></td>\n<td style=\"text-align:left\">Periodically delete specific cache files, temporary files, or reset the printing system.</td>\n</tr>\n<tr>\n<td style=\"text-align:left\"><strong>Advanced Install</strong></td>\n<td style=\"text-align:left\">Install Homebrew, Rosetta 2, or call Installomator for automated software updates.</td>\n</tr>\n<tr>\n<td style=\"text-align:left\"><strong>Inventory Reporting</strong></td>\n<td style=\"text-align:left\">Collect info outside standard fields (e.g. battery health) and report it to <strong>Extension Attributes</strong>.</td>\n</tr>\n<tr>\n<td style=\"text-align:left\"><strong>Permission Management</strong></td>\n<td style=\"text-align:left\">Temporarily grant Admin rights to a user and remove them after a set duration.</td>\n</tr>\n<tr>\n<td style=\"text-align:left\"><strong>AI Automation</strong></td>\n<td style=\"text-align:left\">Pre-trigger local indexing or semantic search initialization for Apple Intelligence models.</td>\n</tr>\n<tr>\n<td style=\"text-align:left\"><strong>Swift Scripting</strong></td>\n<td style=\"text-align:left\"><strong>2026 Trend</strong>: Use Swift for safer, more efficient automation supporting native APIs.</td>\n</tr>\n</tbody>\n</table>\n<h2>2026 Trend: DDM is Replacing “Repetitive Scripts”</h2>\n<p>While scripts were previously used to check system states periodically, macOS 26 recommends using <strong>Declarative Device Management (DDM)</strong>.</p>\n<ul>\n<li><strong>Example</strong>: Instead of a script that periodically deletes large caches in <code>/tmp/</code>, you can define a DDM policy that allows the system to perform “Self-Healing” in place, which is more efficient and real-time.</li>\n</ul>\n<h2>Setup and Deployment Flow (SOP):</h2>\n<h3>1. Write the Script</h3>\n<ul>\n<li>Use <strong>Zsh</strong> (<code>#!/bin/zsh</code>), the default shell for modern macOS. <strong>Note</strong>: Python 2.7 has been removed since macOS 12.3; you must deploy your own interpreter to run Python scripts.</li>\n</ul>\n<h3>2. Upload to Jamf Pro</h3>\n<ul>\n<li>Go to <strong>Settings &gt; Computer Management &gt; Scripts</strong>.</li>\n<li>Click <strong>+ New</strong>, enter a name, and paste your script content.</li>\n<li><strong>Parameters</strong>: You can set labels for variables <code>$4</code> through <code>$11</code>, allowing the same script to take different inputs (e.g., a printer IP) via different policies.</li>\n</ul>\n<h3>3. Execute via Policy</h3>\n<ul>\n<li>Go to <strong>Computers &gt; Policies &gt; + New</strong>.</li>\n<li>Set a <strong>Trigger</strong> (e.g., Recurring Check-in, Login).</li>\n<li>Add the <strong>Scripts</strong> payload and select your uploaded script.</li>\n<li>Set the <strong>Scope</strong> for the target computers.</li>\n</ul>\n<h3>4. Execution Frequency</h3>\n<ul>\n<li>Define the frequency (e.g., <strong>Once per computer</strong> or <strong>Ongoing</strong> for every trigger).</li>\n</ul>\n<h2>Practical Example: Displaying a Notice with <code>jamfHelper</code></h2>\n<p><code>jamfHelper</code> is a powerful notification tool built into Jamf, located at <code>/Library/Application Support/Jamf/bin/jamfHelper.app</code>.</p>\n<pre><code class=\"language-bash\">#!/bin/bash\n\n# Define variables\n\nHELPER=&quot;/Library/Application Support/JAMF/bin/jamfHelper.app/Contents/MacOS/jamfHelper&quot;\n\nTITLE=&quot;School IT Department Announcement&quot;\n\nHEADING=&quot;Software Update Notification&quot;\n\nDESC=&quot;Your computer will undergo a security update in 10 minutes. Please save your work and connect to power.&quot;\n\n# Execute window\n\n&quot;$HELPER&quot; -windowType utility -title &quot;$TITLE&quot; -heading &quot;$HEADING&quot; -description &quot;$DESC&quot; -button1 &quot;I understand&quot; -defaultButton 1\n\n</code></pre>\n<h2>Practical Advice &amp; Expert Tips:</h2>\n<ul>\n<li><strong>Permissions</strong>: Scripts run by Jamf Pro default to <strong>Root</strong> status. Always test on a pilot device to avoid accidental deletion of critical system files.</li>\n<li><strong>Running as User</strong>: To run a command as the currently logged-in user (e.g., to modify their Dock), use: <code>sudo -u $(stat -f%Su /dev/console) command</code>.</li>\n</ul>\n",
          "important": false,
          "tags": [
            "Automation",
            "Shell Script",
            "Zsh",
            "Policies",
            "Scripts",
            "jamfHelper"
          ],
          "category": "Section 7: Advanced Mac Management"
        },
        {
          "id": "mac-10",
          "question": "Default Jamf Pro inventory lacks specific info (like file versions or last reboot). How do I collect custom data?",
          "answer": "<p><strong>Use the “Computer Extension Attributes” feature. This is the core tool in Jamf Pro for expanding database fields and collecting non-standard hardware/software information.</strong></p>\n<p>While standard inventory includes specs, OS versions, and app lists, specific needs (such as checking if a config file was tampered with, battery cycle counts, or custom asset tags) require Extension Attributes.</p>\n<h2>2026 Model: DDM Status Channel</h2>\n<p>In addition to traditional inventory updates, macOS 26 recommends using the DDM Status Channel:</p>\n<ul>\n<li>\n<p><strong>Real-time</strong>: When a state changes (e.g., CPU load, disk space, FileVault status), the device actively reports to Jamf Pro rather than waiting for the next scheduled scan.</p>\n</li>\n<li>\n<p><strong>Low Load</strong>: Only changed fields are reported, significantly reducing server overhead.</p>\n</li>\n<li>\n<p><strong>Recommendation</strong>: For fields where accuracy is critical (e.g., whether security software is running), prioritize the DDM Status Channel.</p>\n</li>\n</ul>\n<h2>Setup Steps (SOP):</h2>\n<h3>1. Navigate</h3>\n<p>Go to <strong>Settings &gt; Computer Management &gt; Extension Attributes</strong>.</p>\n<h3>2. Add</h3>\n<p>Click <strong>+ New</strong>.</p>\n<h3>3. Configure</h3>\n<ul>\n<li><strong>Display Name</strong>: e.g., “Last Reboot Time”.</li>\n<li><strong>Input Type</strong>: Select <strong>Script</strong>.</li>\n<li><strong>Data Type</strong>: String, Integer, or Date. This affects Smart Group logic (e.g., “greater than/less than” vs. “contains”).</li>\n</ul>\n<h3>4. Write Script</h3>\n<ul>\n<li>Paste your Shell Script in the editor.</li>\n<li><strong>Crucial Syntax</strong>: Jamf Pro only reads values enclosed in <code>&lt;result&gt;</code> and <code>&lt;/result&gt;</code> tags. Any other <code>echo</code> output will only appear in debug logs and won’t be written to the database.</li>\n</ul>\n<h2>Practical Example: Collecting “System Uptime Days”</h2>\n<pre><code class=\"language-bash\">#!/bin/bash\n\n# Get system uptime days and report to Jamf Pro\n\n# Uses awk to grab the 'days' part of the uptime command output\n\ndays=$(uptime | awk '{ print $3 }')\n\necho &quot;&lt;result&gt;$days&lt;/result&gt;&quot;\n\n</code></pre>\n<h2>Advanced Application Scenarios:</h2>\n<ul>\n<li><strong>Compliance Check</strong>: Use a script to check if a security daemon (like CrowdStrike or SentinelOne) is running. If it returns “Stopped,” the computer can automatically fall into a “Non-Compliant Group” and trigger a remediation policy.</li>\n<li><strong>Administrative Management</strong>: Set Input Type to <strong>Pop-up Menu</strong> for fields like “Department” (e.g., Academic, Administrative, IT). This allows admins to manually assign units during device issuance for easier group management.</li>\n</ul>\n<h2>Practical Advice: Expert Tips</h2>\n<ul>\n<li><strong>Execution Performance</strong>: Extension Attribute scripts run during <strong>every</strong> inventory update. Avoid time-consuming scripts (like <code>find /</code> scanning the whole drive), as they can slow down inventory reporting across the school or cause system lag.</li>\n</ul>\n",
          "important": false,
          "tags": [
            "Extension Attributes",
            "Scripts",
            "Inventory",
            "Custom Fields"
          ],
          "category": "Section 7: Advanced Mac Management"
        },
        {
          "id": "mac-11",
          "question": "Why does my Mac show 'Unidentified Developer' or 'Cannot be opened' when installing software?",
          "answer": "<p><strong>This is macOS’s Gatekeeper security mechanism. For software required for teaching that has not been notarized by Apple, we recommend using ‘Right-click to Open’ or deploying via MDM to bypass quarantine flags.</strong></p>\n<p>Apple requires all macOS software to undergo <strong>Notarization</strong> to ensure it is free of malicious code. If software is older or the developer is not registered with Apple, it will be blocked.</p>\n<h2>User-Side Solutions (SOP):</h2>\n<h3>Option 1: Right-click to Open (Single Override)</h3>\n<p>This is the standard way to bypass the block without lowering overall system security.</p>\n<ol>\n<li>\n<p>Find the app in <strong>Finder</strong>.</p>\n</li>\n<li>\n<p>Hold the <strong>Control</strong> key (or right-click) and select <strong>Open</strong>.</p>\n</li>\n<li>\n<p>The resulting dialog will now include an <strong>Open</strong> button. Once selected, the system adds this app to a local allowlist.</p>\n</li>\n</ol>\n<h3>Option 2: System Settings Override</h3>\n<ol>\n<li>When the block message appears, click “OK.”</li>\n<li>Go to <strong>System Settings &gt; Privacy &amp; Security</strong>.</li>\n<li>Under the “Security” section, look for “[App Name] was blocked” and click <strong>Open Anyway</strong>.</li>\n<li>Authenticate with an administrator password to run the app.</li>\n</ol>\n<h2>Administrator Solutions (Jamf Pro):</h2>\n<h3>Strategy 1: Deploy via Policy (Recommended)</h3>\n<p>When software is installed via a Jamf Pro Policy, it is written by the Jamf Binary with Root privileges. This typically <strong>does not</strong> apply the “Download Quarantine” attribute (<code>com.apple.quarantine</code>), allowing the app to open without a Gatekeeper warning.</p>\n<h3>Strategy 2: Remove Quarantine Attribute via Script</h3>\n<p>If software was downloaded or copied manually, you can use a Jamf script to strip the quarantine flag:</p>\n<pre><code class=\"language-bash\">\n# Remove quarantine attribute for a specific app\n\nxattr -r -d com.apple.quarantine /Applications/AppName.app\n\n</code></pre>\n<h2>Practical Advice:</h2>\n<p>If you see a message stating the app is <strong>“Damaged and should be moved to the Trash,”</strong> it often isn’t actually corrupt. Instead, its signing certificate may have expired or it hasn’t been notarized. Using the script command above often resolves this issue.</p>\n",
          "important": false,
          "tags": [
            "Gatekeeper",
            "Security",
            "Notarization",
            "Software Installation"
          ],
          "category": "Section 7: Advanced Mac Management"
        },
        {
          "id": "mac-12",
          "question": "How do I prevent students from entering Recovery Mode to format the computer?",
          "answer": "<p><strong>The protection mechanism differs depending on the Mac architecture: Intel-based Macs require a ‘Firmware Password,’ while Apple Silicon (M-series) Macs require a ‘Recovery Lock.’ Both can be deployed via Jamf Pro.</strong></p>\n<p>Recovery Mode is powerful. If left unprotected, anyone with physical access can “Erase Disk” or “Reinstall OS” to bypass school management.</p>\n<h2>Comparison of Mechanisms:</h2>\n<table>\n<thead>\n<tr>\n<th style=\"text-align:left\">Architecture</th>\n<th style=\"text-align:left\">Protection Mechanism</th>\n<th style=\"text-align:left\">Deployment Method</th>\n</tr>\n</thead>\n<tbody>\n<tr>\n<td style=\"text-align:left\"><strong>Apple Silicon (M1-M5)</strong></td>\n<td style=\"text-align:left\"><strong>Recovery Lock</strong></td>\n<td style=\"text-align:left\">Configured via <strong>MDM Remote Command</strong> only</td>\n</tr>\n<tr>\n<td style=\"text-align:left\"><strong>Intel Mac</strong></td>\n<td style=\"text-align:left\"><strong>Firmware Password</strong></td>\n<td style=\"text-align:left\">Configured via <strong>Configuration Profile</strong> or Command</td>\n</tr>\n</tbody>\n</table>\n<h3>1. Recovery Lock (For Apple Silicon)</h3>\n<p>Starting with macOS 11.5, MDM can set a Recovery Lock. When enabled, the Mac will prompt for the administrator-defined password before allowing entry into Recovery Mode.</p>\n<ul>\n<li>\n<p><strong>Jamf Pro Action</strong>: Select a computer &gt; <strong>Management &gt; Remote Commands &gt; Set Recovery Lock</strong>.</p>\n</li>\n<li>\n<p><strong>Management Note</strong>: Jamf Pro will escrow the password so you can retrieve it later from the inventory record.</p>\n</li>\n</ul>\n<h3>2. Firmware Password (For Intel Macs)</h3>\n<p>This prevents the Mac from booting from anything other than the designated startup disk without a password.</p>\n<ul>\n<li><strong>Jamf Pro Action</strong>: Create a <strong>Computer Configuration Profile</strong> with the <strong>EFI Password</strong> payload.</li>\n</ul>\n<h2>Practical Advice:</h2>\n<p>Setting these locks is a fundamental security requirement for shared labs or student 1:1 laptops. Without them, “Remote Management” can be circumvented via a hard reset and disk wipe in the Recovery environment.</p>\n",
          "important": false,
          "tags": [
            "Tamper Proofing",
            "Recovery Lock",
            "Firmware Password",
            "Security"
          ],
          "category": "Section 7: Advanced Mac Management"
        },
        {
          "id": "mac-13",
          "question": "Google Meet or Zoom keeps asking for 'Screen Recording' permissions. Can MDM enable this automatically?",
          "answer": "<p><strong>This is governed by macOS TCC (Transparency, Consent, and Control) privacy mechanisms. For ‘Screen Recording,’ ‘Microphone,’ and ‘Camera,’ Apple mandates that the user must ‘personally click to allow.’</strong></p>\n<p>MDM cannot forcibly “turn on” these permissions. However, you can use a <strong>PPPC (Privacy Preferences Policy Control)</strong> profile in Jamf Pro to authorize “Standard Users” (teachers) to approve these requests without needing an administrator password.</p>\n<h2>MDM Control Capability Matrix (2026 Edition)</h2>\n<table>\n<thead>\n<tr>\n<th style=\"text-align:left\">Permission</th>\n<th style=\"text-align:left\">Forced ON by MDM?</th>\n<th style=\"text-align:left\">User Consent Needed?</th>\n<th style=\"text-align:left\">Admin Strategy</th>\n</tr>\n</thead>\n<tbody>\n<tr>\n<td style=\"text-align:left\"><strong>Screen Recording</strong></td>\n<td style=\"text-align:left\">❌ No</td>\n<td style=\"text-align:left\">✅ Yes</td>\n<td style=\"text-align:left\">Authorize Standard Users to allow</td>\n</tr>\n<tr>\n<td style=\"text-align:left\"><strong>Microphone / Camera</strong></td>\n<td style=\"text-align:left\">❌ No</td>\n<td style=\"text-align:left\">✅ Yes</td>\n<td style=\"text-align:left\">Set to “Allow” (prevents blocking)</td>\n</tr>\n<tr>\n<td style=\"text-align:left\"><strong>Accessibility</strong></td>\n<td style=\"text-align:left\">✅ Yes</td>\n<td style=\"text-align:left\">❌ No</td>\n<td style=\"text-align:left\">Can be fully authorized silently</td>\n</tr>\n<tr>\n<td style=\"text-align:left\"><strong>Full Disk Access</strong></td>\n<td style=\"text-align:left\">✅ Yes</td>\n<td style=\"text-align:left\">❌ No</td>\n<td style=\"text-align:left\">Can be fully authorized silently</td>\n</tr>\n</tbody>\n</table>\n<h2>Best Practices for Schools (SOP):</h2>\n<h3>1. Solve the ‘Standard User’ Block (Crucial)</h3>\n<p>Since teachers are rarely administrators, they get stuck when a system prompt asks for an admin password to allow screen sharing.</p>\n<ul>\n<li>\n<p><strong>Fix</strong>: Create a PPPC payload in Jamf Pro for the specific app (e.g., Zoom).</p>\n</li>\n<li>\n<p><strong>Setting</strong>: Set <code>Screen Recording</code> to <strong>Allow Standard Users to allow access</strong>.</p>\n</li>\n<li>\n<p><strong>Result</strong>: When the teacher clicks allow, the system <strong>no longer asks for an admin password</strong>.</p>\n</li>\n</ul>\n<h3>2. Silent Authorization</h3>\n<p>For specialized tools, set <strong>Accessibility</strong> to <strong>Allow</strong> to reduce pop-up fatigue for your users.</p>\n<h2>Practical Advice:</h2>\n<p>If your PPPC profile isn’t working, check your <strong>Bundle ID</strong> and <strong>Code Requirement</strong>. Use the “PPPC Utility” (free open-source tool) to generate exact signature codes for Jamf Pro.</p>\n<p><strong>Note</strong>: macOS 26 has increased the frequency of “Screen Recording” persistence notifications. Even when authorized, the system will occasionally remind users that an app is observing the screen. Inform staff that this is a normal security feature.</p>\n",
          "important": false,
          "tags": [
            "PPPC",
            "Privacy",
            "TCC",
            "Screen Recording",
            "Standard Users"
          ],
          "category": "Section 7: Advanced Mac Management"
        },
        {
          "id": "mac-14",
          "question": "How do I deploy multiple network printers to teacher Macs using Jamf Pro?",
          "answer": "<p><strong>Modern Mac printing should prioritize the ‘AirPrint (driverless)’ protocol. For advanced configurations, use ‘Policies’ or Shell scripts executing the <code>lpadmin</code> command.</strong></p>\n<p>Since macOS 12 Monterey, Apple has shifted towards IPP/AirPrint, significantly reducing the need for vendor-specific PPD drivers.</p>\n<h2>Deployment Strategies:</h2>\n<h3>Method 1: Native Jamf Pro UI (Best for Beginners)</h3>\n<ol>\n<li><strong>Add Printer</strong>: Go to <strong>Settings &gt; Computer Management &gt; Printers</strong>.</li>\n<li>Enter the IP and Display Name.</li>\n<li><strong>Key</strong>: If the printer supports AirPrint, select <strong>Generic PCL Laser Printer</strong> or <strong>Generic PostScript Printer</strong>. No vendor driver is needed.</li>\n<li><strong>Policy</strong>: Create a policy to install this printer. Set the trigger to <strong>Self Service</strong> so teachers can install only the printers they need for their specific office.</li>\n</ol>\n<h3>Method 2: Shell Script (Advanced / Driverless)</h3>\n<p>For precise control, use a script to call <code>lpadmin</code>:</p>\n<pre><code class=\"language-bash\">#!/bin/bash\n\n# Define Variables\n\nPRINTER_NAME=&quot;Office_HP_M404&quot;\n\nDISPLAY_NAME=&quot;Admin Office HP M404&quot;\n\nADDRESS=&quot;ipp://192.168.1.100/ipp/print&quot;\n\n# Execute lpadmin with -m everywhere for auto-AirPrint\n\n/usr/sbin/lpadmin -p &quot;$PRINTER_NAME&quot; -D &quot;$DISPLAY_NAME&quot; -E -v &quot;$ADDRESS&quot; -m everywhere -o printer-is-shared=false\n\necho &quot;Printer $DISPLAY_NAME installed successfully.&quot;\n\n</code></pre>\n<h3>Method 3: Handling Older Printers (Driver Required)</h3>\n<ol>\n<li>Download the vendor <code>.pkg</code> and upload it to Jamf Pro.</li>\n<li>Create a policy to install the <code>.pkg</code> first.</li>\n<li>Use <code>lpadmin</code> with the specific PPD path (e.g., <code>-P &quot;/Library/Printers/PPDs/Contents/Resources/HP.gz&quot;</code>).</li>\n</ol>\n<h2>Practical Advice:</h2>\n<p><strong>Use Self Service</strong>. Deploying dozens of printers automatically creates a cluttered menu for teachers. By placing printers in Self Service with clear names (e.g., “Install - 2F Staff Room Printer”), you minimize confusion and support calls.</p>\n",
          "important": false,
          "tags": ["Printers", "AirPrint", "lpadmin", "Policy", "Self Service"],
          "category": "Section 7: Advanced Mac Management"
        },
        {
          "id": "mac-15",
          "question": "How do I mass-deploy Microsoft Office and activate licenses? Lab vs. Administrative Macs?",
          "answer": "<p><strong>The best practice is to use ‘Jamf App Installers’ for automated deployment, combined with either the ‘Volume License Serializer’ or ‘User-based Login’ depending on the scenario.</strong></p>\n<p>Always use the Microsoft CDNs or Jamf-provided installers. <strong>Avoid the Mac App Store versions</strong>, as they do not support Volume Licensing (VL) features correctly for all scenarios.</p>\n<h2>Scenario 1: Computer Labs / Shared Kiosks (Device-Based)</h2>\n<p>Labs must be “ready-to-use” without requiring individual student logins for Office.</p>\n<ol>\n<li>\n<p><strong>Installer</strong>: Deploy Office 365 via Jamf Pro <strong>App Installers</strong>.</p>\n</li>\n<li>\n<p><strong>Activation (Crucial)</strong>: Download the <strong>Volume License Serializer (.pkg)</strong> from the Microsoft VLSC.</p>\n</li>\n<li>\n<p><strong>Policy</strong>: Create a Jamf Pro policy to install this Serializer.</p>\n</li>\n<li>\n<p><strong>Result</strong>: Office will activate against “the machine” itself. Any user can open Word and begin working immediately without a prompt.</p>\n</li>\n</ol>\n<h2>Scenario 2: Faculty / Staff Macs (User-Based)</h2>\n<p>Staff typically have individual Microsoft 365 (A3/A5) accounts.</p>\n<ol>\n<li>\n<p><strong>Installer</strong>: Deploy via <strong>App Installers</strong> to keep software updated automatically.</p>\n</li>\n<li>\n<p><strong>Activation</strong>: Do <strong>not</strong> deploy the Serializer. The user simply signs in with their school email when they first open the app.</p>\n</li>\n<li>\n<p><strong>Benefit</strong>: Enables personal cloud storage (OneDrive) and document syncing.</p>\n</li>\n</ol>\n<h2>Practical Advice:</h2>\n<p>If you encounter license conflicts, it’s usually because of residual older Serializers. Use the official <strong>Microsoft License Removal Tool</strong> (run as a script via Jamf) to clean the machine before a fresh deployment.</p>\n",
          "important": false,
          "tags": [
            "Office",
            "Microsoft 365",
            "Serializer",
            "Volume License",
            "Jamf App Installers"
          ],
          "category": "Section 7: Advanced Mac Management"
        },
        {
          "id": "mac-16",
          "question": "How do I manage or disable 'iPhone Mirroring' in macOS Sequoia?",
          "answer": "<p><strong>While convenient, ‘iPhone Mirroring’ in macOS 15+ poses Data Loss Prevention (DLP) risks on shared school computers. It should be managed via MDM.</strong></p>\n<h2>The Privacy Risk:</h2>\n<p>When a personal iPhone is mirrored to a school Mac, notifications, photos, and app content are visible on the Mac screen. It also supports file drag-and-drop, which could lead to unauthorized data transfer.</p>\n<h2>Jamf Pro Configuration:</h2>\n<ol>\n<li>Go to <strong>Computers &gt; Configuration Profiles &gt; Restrictions</strong>.</li>\n<li>Navigate to the macOS 26 (Tahoe) section.</li>\n<li><strong>Option A (Full Block)</strong>: Uncheck <strong>Allow iPhone Mirroring</strong>.</li>\n<li><strong>Option B (Granular)</strong>: Use the <strong>View Only</strong> mode or uncheck <strong>Allow file and clipboard sync</strong>.</li>\n</ol>\n<h2>Result:</h2>\n<p>Once applied, the iPhone Mirroring app on the Mac will display a “Disabled by Administrator” message when launched. We recommend disabling this in computer labs while potentially allowing it on assigned teacher laptops with restrictions on file sync.</p>\n",
          "important": false,
          "tags": [
            "macOS 15",
            "iPhone Mirroring",
            "Privacy",
            "Restrictions",
            "DLP"
          ],
          "category": "Section 7: Advanced Mac Management"
        },
        {
          "id": "mac-17",
          "question": "What are the advantages of using the Mac mini (M4/M5) for school labs?",
          "answer": "<p><strong>The Mac mini (M4/M5), paired with macOS 26, offers ‘Zero-Touch Deployment’ and extreme energy efficiency, making it the ideal PC replacement for modern schools.</strong></p>\n<h2>Why Administrators Choose Mac mini:</h2>\n<h3>1. Zero-Wipe Migration</h3>\n<ul>\n<li><strong>Traditional PC</strong>: Requires “Ghosting” or heavy image deployment via network.</li>\n<li><strong>Mac mini (M5)</strong>: Supports <strong>Zero-Wipe MDM Migration</strong> in macOS 26. This means if you change MDM providers, you can migrate the machine’s ownership “in place” without wiping the drive or reinstalling educational software.</li>\n<li><strong>ADE Automation</strong>: Unbox, plug in, and the machine automatically installs Office, Adobe, and network settings based on its serial number.</li>\n<li><strong>Reset</strong>: Execute an EACS command to reset to factory state in minutes.</li>\n</ul>\n<h3>2. Space and Energy Efficiency</h3>\n<ul>\n<li>The M4/M5 Mac mini has a tiny footprint (approx. 12.7cm wide) and can be mounted behind monitors.</li>\n<li>Its power consumption is significantly lower than a traditional PC, reducing long-term school electricity costs.</li>\n</ul>\n<h3>3. Local AI Readiness</h3>\n<ul>\n<li>The M4/M5 chips feature a powerful Neural Engine (NPU), capable of running local AI models and 4K video editing without relying on cloud credits, perfectly aligning with modern digital curricula.</li>\n</ul>\n",
          "important": false,
          "tags": ["Mac mini", "M4", "Lab Setup", "Zero-Touch", "ADE"],
          "category": "Section 7: Advanced Mac Management"
        },
        {
          "id": "mac-18",
          "question": "A Mac is locked by a former user's Apple ID (Activation Lock). How do I recover it?",
          "answer": "<p><strong>If the Mac is a school asset (enrolled in ASM), administrators can bypass Activation Lock directly from the Apple School Manager portal without the original user’s password.</strong></p>\n<p>This is a critical failsafe for when staff leave or students graduate without signing out of their personal accounts.</p>\n<h2>Standard Recovery SOP:</h2>\n<ol>\n<li>\n<p><strong>Log in to ASM</strong>: Use your administrator account at <a href=\"https://school.apple.com\">school.apple.com</a>.</p>\n</li>\n<li>\n<p><strong>Search Device</strong>: Click <strong>Devices</strong> in the sidebar and enter the Mac’s serial number.</p>\n</li>\n<li>\n<p><strong>Execute Unlock</strong>:</p>\n<ul>\n<li>Locate the <strong>Activation Lock</strong> status in the details pane.</li>\n<li>Click <strong>Turn Off</strong> or <strong>Clear Unlock Code</strong>.</li>\n</ul>\n</li>\n<li>\n<p><strong>Reset Device</strong>:</p>\n<ul>\n<li>Wait a few minutes for the command to propagate.</li>\n<li>Put the Mac into <strong>Recovery Mode</strong> and reinstall macOS. The lock screen will no longer appear.</li>\n</ul>\n</li>\n</ol>\n<h2>Prerequisites:</h2>\n<ul>\n<li>The device must be part of your <strong>Automated Device Enrollment (ADE)</strong> pool and assigned to your MDM.</li>\n<li>For older machines purchased outside the project, they must have been added to ASM via Apple Configurator for this feature to work.</li>\n</ul>\n",
          "important": false,
          "tags": ["Activation Lock", "ASM", "Unlocking", "Asset Recovery"],
          "category": "Section 7: Advanced Mac Management"
        },
        {
          "id": "mac-19",
          "question": "2026 macOS Deployment: Advanced strategies for large-scale enrollment.",
          "answer": "<p><strong>In 2026, Zero-Touch deployment via ADE is the enterprise standard. However, the bottleneck for high-volume rollouts (like a 50-unit Mac mini lab) remains network bandwidth and MDM server load.</strong></p>\n<h2>I. Core Strategies for 2026</h2>\n<h3>1. Content Caching Server</h3>\n<p>This is the lifeblood of mass deployment.</p>\n<ul>\n<li>\n<p><strong>Implementation</strong>: Dedicate one Mac mini (M5) to this role for each computer lab or department building.</p>\n</li>\n<li>\n<p><strong>Benefit</strong>: When the first Mac downloads Office or a macOS update, the other 49 units will pull it locally from the cache at near-instant speeds, protecting your school’s external internet pipe.</p>\n</li>\n</ul>\n<h3>2. Declarative Enrollment (DDM)</h3>\n<p>macOS 26 supports a more resilient enrollment engine.</p>\n<ul>\n<li>\n<p><strong>Feature</strong>: Instead of waiting for the server to push commands, the device “declares” its target state the moment it joins.</p>\n</li>\n<li>\n<p><strong>Result</strong>: This improves software install success rates by approx. 30% especially on campus Wi-Fi environments.</p>\n</li>\n</ul>\n<h2>II. Offline Installation and Special Environments</h2>\n<p>For schools with unstable internet, use a hybrid strategy:</p>\n<ol>\n<li>\n<p><strong>PKG Pre-load Strategy</strong>: Use an external high-speed SSD to pre-load large offline packages (like Adobe CC). Use a post-enrollment script to call <code>/usr/sbin/installer</code> locally from the internal drive to finish the setup quickly.</p>\n</li>\n<li>\n<p><strong>IP Signal Staggering</strong>: Stagger the deployment volume into different time slots, utilizing Jamf Pro’s “Staggered execution” features if available.</p>\n</li>\n</ol>\n<h2>III. 2026 NPU Considerations</h2>\n<p>The <strong>M4/M5</strong> chips feature powerful Neural Engines. During your initial deployment, ensure you aren’t over-restricting background tasks, as macOS uses this time to initialize local AI models (for Writing Tools and Siri). Allowing this process to finish during setup ensures students have a smooth “Day One” experience.</p>\n",
          "important": false,
          "tags": [
            "Deployment",
            "ADE",
            "Offline Install",
            "Content Caching",
            "macOS 26"
          ],
          "category": "Section 7: Advanced Mac Management"
        },
        {
          "id": "mac-20",
          "question": "How do I configure 'Unlock FileVault via SSH' in macOS 26?",
          "answer": "<p><strong>macOS 26 introduces the ability to unlock FileVault at the ‘Pre-boot’ stage via SSH, solving a major pain point for headless server management.</strong></p>\n<h2>Problem Background</h2>\n<p>Historically, a Mac with FileVault enabled would stop at the login screen after a reboot, before the network or remote access services started. This required physical keyboard access to unlock and “lost” the machine to remote admins.</p>\n<h2>Requirements</h2>\n<ol>\n<li><strong>Remote Login</strong>: Must be enabled in System Settings &gt; General &gt; Sharing. (Or pushed via MDM <code>com.apple.RemoteManagement</code>).</li>\n<li><strong>Network</strong>: A hardwired Ethernet connection is most reliable for Pre-boot networking.</li>\n<li><strong>Authorization</strong>: The SSH user must be a FileVault-enabled user.</li>\n<li><strong>OS</strong>: macOS 26 or later.</li>\n</ol>\n<h2>Remote Unlock Command</h2>\n<p>From a remote terminal:</p>\n<p><code>SSH -o PreferredAuthentications=password -o PubkeyAuthentication=no username@mac-ip</code></p>\n<p>After entering the password, the SSH session will momentarily drop as the encryption keys are released and the system finishes its boot sequence.</p>\n<h2>Security Risks &amp; Mitigation</h2>\n<table>\n<thead>\n<tr>\n<th style=\"text-align:left\">Risk</th>\n<th style=\"text-align:left\">Mitigation Measure</th>\n</tr>\n</thead>\n<tbody>\n<tr>\n<td style=\"text-align:left\">Brute Force</td>\n<td style=\"text-align:left\">Limit source IP, use firewall, strong passwords, change default port</td>\n</tr>\n<tr>\n<td style=\"text-align:left\">Man-in-the-Middle</td>\n<td style=\"text-align:left\">Verify host keys, use VPN</td>\n</tr>\n<tr>\n<td style=\"text-align:left\">Network Sniffing</td>\n<td style=\"text-align:left\">Dedicated management VLAN, Network Access Control (NAC)</td>\n</tr>\n</tbody>\n</table>\n<h2>2026 Safety Warning (M5 Macs)</h2>\n<p>On <strong>M5 Silicon</strong> Macs, Apple has tightened <strong>Secure Enclave</strong> protections.</p>\n<ul>\n<li>\n<p>If you have enabled “Lockdown Mode” or “Advanced Data Protection,” the Pre-boot SSH stack may be crippled for safety.</p>\n</li>\n<li>\n<p><strong>Recommendation</strong>: For server-room units requiring remote telemetry, ensure these high-restriction security toggles are managed carefully via MDM to allow the network stack to initialize.</p>\n</li>\n</ul>\n<h2>Deployment Advice</h2>\n<ul>\n<li><strong>Recommended</strong>: Server-room Mac minis, headless units, and multi-campus environments.</li>\n<li><strong>Not Recommended</strong>: Student labs, public kiosks, or unsecured network segments.</li>\n</ul>\n",
          "important": false,
          "tags": [
            "FileVault",
            "SSH",
            "Remote Unlock",
            "macOS 26",
            "Remote Management"
          ],
          "category": "Section 7: Advanced Mac Management"
        },
        {
          "id": "mac-21",
          "question": "macOS 26 Transparency: Students can see MDM privacy settings. How do I handle questions?",
          "answer": "<p><strong>macOS 26 explicitly labels privacy permissions (Camera, Mic, Screen Recording) that are managed by the organization in System Settings.</strong></p>\n<h2>Interface Changes</h2>\n<h3>Pre-macOS 26 (Before macOS 15 Sequoia)</h3>\n<ul>\n<li>Users saw toggles as grayed out but often didn’t know <em>why</em>.</li>\n<li>Permission switches were simply locked without explanation.</li>\n</ul>\n<h3>macOS 26</h3>\n<ul>\n<li>Displays a badge: <strong>“Managed by [Organization Name]”</strong>.</li>\n<li>Displays management icons.</li>\n<li>Users can see what has been authorized but still cannot change it, but now they know it is set by the school.</li>\n</ul>\n<h2>Common Questions and Response Angles</h2>\n<h3>“Why is the Microphone forced ON?”</h3>\n<ul>\n<li>Response: This ensures apps like Zoom, Google Meet, or recording software for language classes work instantly.</li>\n<li>Having the permission does not mean it is “Recording”—macOS still shows a hardware-level <strong>Orange Light</strong> whenever the mic is active (this cannot be bypassed by software).</li>\n</ul>\n<h3>“Is Screen Recording for monitoring me?”</h3>\n<ul>\n<li>Response: This allows students to share their screen during presentations or remote lab sessions.</li>\n<li>Having the permission allows the app to share; it does not mean continuous monitoring.</li>\n<li>macOS displays a <strong>Green indicator</strong> when the screen is being shared or recorded.</li>\n</ul>\n<h3>“Why can’t I turn it OFF?”</h3>\n<ul>\n<li>Response: Managing these via MDM ensures that critical educational tools don’t fail due to a student accidentally clicking “Deny.”</li>\n<li>This reduces the support burden of repeatedly troubleshooting permission prompts.</li>\n</ul>\n<h2>Practical Advice:</h2>\n<h3>Preparation</h3>\n<ul>\n<li>List the permissions the school has set and explain the purpose of each.</li>\n<li>Prepare an FAQ for students/staff.</li>\n<li>Explain that this is a new design feature of macOS 26, not a new monitoring initiative.</li>\n</ul>\n<h3>Response Principles</h3>\n<ul>\n<li>Acknowledge that privacy concerns are valid.</li>\n<li>Explain the pedagogical necessity of each permission.</li>\n<li>Emphasize macOS’s built-in protections (hardware indicators, notifications).</li>\n</ul>\n",
          "important": false,
          "tags": [
            "Privacy Permissions",
            "Transparency",
            "PPPC",
            "macOS 26",
            "Communication"
          ],
          "category": "Section 7: Advanced Mac Management"
        },
        {
          "id": "mac-22",
          "question": "macOS 26: The end of the Intel Mac era. How much longer can Intel Macs be used?",
          "answer": "<p><strong>macOS 26 (Tahoe) has been confirmed as the final major version of macOS to support Intel-based Macs. Starting with macOS 27 in 2027, the operating system will exclusively support Apple Silicon (M1–M5 series).</strong></p>\n<h2>Support Roadmap and Retirement Timeline</h2>\n<h3>1. The Last Supported Intel Macs</h3>\n<ul>\n<li><strong>iMac (Retina 5K, 27-inch, 2020)</strong>: The peak of Intel Mac performance.</li>\n<li><strong>MacBook Pro (16-inch, 2019)</strong>.</li>\n<li><strong>Mac Pro (2019+)</strong>.</li>\n<li><strong>Note</strong>: Older models (2017 and prior) are already unsupported by modern macOS versions and can only run older system versions.</li>\n</ul>\n<h3>2. macOS 27 (Expected Late 2026/2027)</h3>\n<ul>\n<li>Exclusively supports Apple Silicon (M1/M2/M3/M4/M5).</li>\n<li>Intel Macs will be unable to upgrade.</li>\n</ul>\n<h2>Lifecycle Expectations</h2>\n<h3>1. Security Updates</h3>\n<ul>\n<li>After macOS 26 stops receiving major feature updates, Apple typically provides <strong>2-3 additional years of Security Updates</strong>.</li>\n<li>We expect Intel Macs on macOS 26 to be safe for school use until approximately <strong>late 2028 or early 2029</strong>.</li>\n</ul>\n<h3>2. App Support</h3>\n<ul>\n<li>Major developers (Adobe, Microsoft, Google) usually support the current OS plus two versions back.</li>\n<li>Once security updates for macOS 26 cease, these vendors will likely stop releasing Intel-compatible versions or updates.</li>\n</ul>\n<h2>Assessing Existing Intel Macs</h2>\n<h3>1. Audit via MDM</h3>\n<p>Use Jamf Pro to identify all Intel-based Macs:</p>\n<ul>\n<li>\n<p>Create a <strong>Smart Computer Group</strong>.</p>\n</li>\n<li>\n<p>Criteria: <code>Architecture Type</code> is <code>x86_64</code>.</p>\n</li>\n</ul>\n<h3>2. Impact assessment by Scenario</h3>\n<table>\n<thead>\n<tr>\n<th style=\"text-align:left\">Scenario</th>\n<th style=\"text-align:left\">Impact Assessment</th>\n</tr>\n</thead>\n<tbody>\n<tr>\n<td style=\"text-align:left\"><strong>Professional Labs</strong></td>\n<td style=\"text-align:left\">Software vendors may gradually phase out Intel support.</td>\n</tr>\n<tr>\n<td style=\"text-align:left\"><strong>Administrative Tasks</strong></td>\n<td style=\"text-align:left\">Office and browsers have lower requirements; usable until security updates end.</td>\n</tr>\n<tr>\n<td style=\"text-align:left\"><strong>Teacher Laptops</strong></td>\n<td style=\"text-align:left\">Depends on specific software requirements.</td>\n</tr>\n</tbody>\n</table>\n<h2>Timeline Summary</h2>\n<ul>\n<li><strong>2026–2027</strong>: Intel Macs running macOS 26 remain fully functional with security patches.</li>\n<li><strong>2027–2028</strong>: Third-party software support begins to dwindle.</li>\n<li><strong>2029+</strong>: Security updates end; devices should be replaced or used for non-networked tasks.</li>\n</ul>\n<h2>Why Apple Silicon?</h2>\n<ul>\n<li>M1-M5 series offer revolutionary performance and battery life over Intel.</li>\n<li>macOS and core apps are optimized for the Apple Silicon architecture.</li>\n<li>Native support for running iOS/iPadOS apps.</li>\n</ul>\n",
          "important": true,
          "tags": [
            "Intel Mac",
            "Apple Silicon",
            "System Support",
            "macOS 26",
            "Lifecycle Planning"
          ],
          "category": "Section 7: Advanced Mac Management"
        },
        {
          "id": "mac-23",
          "question": "Classroom Order: How to manage or disable 'iPhone Mirroring' to prevent student distractions.",
          "answer": "<p><strong>macOS 26 provides granular MDM controls for ‘iPhone Mirroring.’ IT coordinators can set different permission levels for ‘Shared Lab Macs’ versus ‘Teacher Presentation Macs.’</strong></p>\n<p>In a school environment, the primary concern is a student operating a shared Mac and mirroring their personal iPhone’s social messages or inappropriate game content, disrupting the class.</p>\n<h2>I. 2026 Management Modes (SOP)</h2>\n<p>Using Jamf Pro’s <strong>Restrictions</strong> payload, you should apply one of these three strategies based on the machine’s Smart Group:</p>\n<ol>\n<li>\n<p><strong>Full Disable (High Security labs)</strong>:</p>\n<ul>\n<li><strong>Best For</strong>: Library open-access Macs, Computer Labs.</li>\n<li><strong>Setting</strong>: Uncheck <code>Allow iPhone Mirroring</code>.</li>\n<li><strong>Effect</strong>: If a student tries to pair their iPhone, they will see a message: “This feature is disabled by your organization.”</li>\n</ul>\n</li>\n<li>\n<p><strong>Forced View-Only (Presentation Focus)</strong>:</p>\n<ul>\n<li><strong>Best For</strong>: Classroom podium Macs used by teachers for projection.</li>\n<li><strong>Setting</strong>: Enable <code>Force View-Only Mirroring</code>.</li>\n<li><strong>Effect</strong>: The iPhone screen can be displayed on the Mac (perfect for demonstrating a student’s mobile project), but the teacher’s Mac keyboard and mouse cannot control the iPhone.</li>\n</ul>\n</li>\n<li>\n<p><strong>Restricted Data Transfer (DLP Focus)</strong>:</p>\n<ul>\n<li><strong>Best For</strong>: Faculty/Staff administrative computers.</li>\n<li><strong>Setting</strong>: Disable <code>Allow File and Clipboard Sync with iPhone Mirroring</code>.</li>\n<li><strong>Effect</strong>: Personal iPhone mirroring is allowed, but the ability to drag-and-drop files between the school Mac and the personal iPhone is blocked to prevent data leakage of school records.</li>\n</ul>\n</li>\n</ol>\n<h2>II. Operational Recommendations</h2>\n<ul>\n<li><strong>Automation Strategy</strong>: Consider using Jamf Pro’s “Time-Based” policies to switch to “View Only” during instructional hours and allow full mirroring after school.</li>\n<li><strong>Monitoring Indicators</strong>: Remind teachers and students that when iPhone Mirroring is active, macOS 26 shows a prominent purple bar in the menu bar, making it easy for teachers to spot during classroom rounds.</li>\n</ul>\n<p><strong>Administrator’s Insight</strong>: For M5 Macs, the mirroring latency is extremely low. We recommend using “View Only” mode as a tool for “Student Work Showcase” rather than outright blocking it, to maximize the value of teaching technology.</p>\n",
          "important": false,
          "tags": [
            "iPhone Mirroring",
            "Classroom Management",
            "Restrictions",
            "macOS 26",
            "Security"
          ],
          "category": "Section 7: Advanced Mac Management"
        },
        {
          "id": "mac-24",
          "question": "Exam Security: Managing Safari 'Distraction Control' to prevent cheating during web-based tests.",
          "answer": "<p><strong>Safari in macOS 26 introduces ‘Distraction Control,’ which allows users to hide specific web elements (like ads or sidebars). However, in a Computer-Based Testing (CBT) environment, students could abuse this to hide timers, navigation menus, or proctoring warnings.</strong></p>\n<h2>I. Risk Scenarios</h2>\n<ul>\n<li><strong>Practice Mode</strong>: Students hide “Hints” or “Rules.”</li>\n<li><strong>Official Testing</strong>: Students hide the “Remaining Time (Countdown)” to claim they didn’t know the exam was ending, or hide the “Proctoring Status Label.”</li>\n</ul>\n<h2>II. MDM Management Solutions (SOP)</h2>\n<p>IT coordinators should enforce the following settings via Jamf Pro during major exams:</p>\n<h3>1. Lock via Configuration Profile (Recommended)</h3>\n<ul>\n<li><strong>Domain</strong>: <code>com.apple.Safari</code> advanced settings.</li>\n<li><strong>Setting</strong>: <code>AllowDistractionControl</code> = <code>false</code></li>\n<li><strong>Effect</strong>: The “Distraction Control” option in the Safari menu will be grayed out and unavailable, ensuring the website UI remains exactly as intended by the test publisher.</li>\n</ul>\n<h3>2. Assessment Mode (AAC)</h3>\n<p>For high-stakes exams, use a specialized testing app or a managed browser that invokes Apple’s <strong>‘Automatic Assessment Configuration (AAC).’</strong></p>\n<ul>\n<li>This mode forces the device into a secure workspace, automatically disabling non-essential features including Distraction Control, Siri, notifications, and multitasking.</li>\n</ul>\n<h2>III. Operational Advice</h2>\n<ol>\n<li><strong>Smart Group Segmentation</strong>: Create a “Testing Mode” group and push the restriction profile only 15 minutes before the exam begins.</li>\n<li><strong>Script Verification</strong>: Use an Extension Attribute to verify that the Safari <code>DistractionControl</code> override is successfully active before the exam starts.</li>\n</ol>\n<p><strong>Administrator’s Insight</strong>: While “Distraction Control” improves daily reading efficiency, it represents a significant loophole for proctoring in school assessment scenarios. We recommend evaluating it alongside the “Safari Translation” feature for potential disabling during tests.</p>\n",
          "important": true,
          "tags": [
            "Safari",
            "Distraction Control",
            "Exam Security",
            "macOS 26",
            "Proctoring"
          ],
          "category": "Section 7: Advanced Mac Management"
        },
        {
          "id": "mac-25",
          "question": "Security Auditing: Using PSSO 2.0 to achieve 'Boot-to-Desktop' and meet strong password requirements.",
          "answer": "<p><strong>In 2026, Platform SSO (PSSO) 2.0 allows schools to solve two major operational problems: weak teacher passwords and the ‘double login’ (FileVault + OS) frustration.</strong> By synchronizing the local Mac login with organizational cloud accounts (Microsoft Entra ID or Google Workspace), you can enforce compliant strong password policies while providing a streamlined single-entry experience for the user.</p>\n<h2>I. Implementation Workflow (SOP)</h2>\n<ol>\n<li>\n<p><strong>Configure PSSO in MDM</strong>:</p>\n<ul>\n<li>Set up the Platform SSO configuration in Jamf Pro.</li>\n<li>Select the authentication mode: <strong>‘Shared Secret’</strong> (standard) or <strong>‘Hardware Bound Key’</strong> (highest security using the Secure Enclave).</li>\n</ul>\n</li>\n<li>\n<p><strong>Enable Boot-to-Desktop</strong>:</p>\n<ul>\n<li>Enable <strong>‘FileVault Login &amp; PSSO Synchronization.’</strong></li>\n<li><strong>Result</strong>: When the teacher enters their password at the initial FileVault disk-unlock screen, the system automatically uses those credentials to complete the cloud authentication in the background. The Mac loads straight to the desktop without asking for a second password.</li>\n</ul>\n</li>\n<li>\n<p><strong>Enforce Strong Policies via IdP</strong>:</p>\n<ul>\n<li>Password strength (length, complexity, rotation) is managed centrally by your Cloud Identity Provider (IdP).</li>\n<li><strong>Benefit</strong>: The school IT lead no longer needs to manually audit every Mac’s local password. As long as the IdP authentication is successful, the device is automatically compliant with national cybersecurity audit standards.</li>\n</ul>\n</li>\n</ol>\n<h2>II. Frequently Asked Questions</h2>\n<ul>\n<li>\n<p><strong>Can users log in while offline?</strong></p>\n<ul>\n<li>Yes. PSSO maintains a local cached credential to ensure teachers can still teach in areas with poor connectivity or while at home.</li>\n</ul>\n</li>\n<li>\n<p><strong>If a teacher changes their password in the cloud, does it update on the Mac?</strong></p>\n<ul>\n<li>Yes. On the next login, the Mac will detect the mismatch, prompt the user to enter their new cloud password, and immediately synchronize the local account.</li>\n</ul>\n</li>\n</ul>\n<h2>III. Operational Recommendations</h2>\n<ol>\n<li><strong>Phased Rollout</strong>: We recommend starting with “Administrative Offices” before expanding to “General Teacher Laptops.”</li>\n<li><strong>MDM Monitoring</strong>: Utilize Jamf’s DDM Status Channel to monitor each Mac’s PSSO sync status and ensure they remain <code>Healthy</code>.</li>\n</ol>\n<p><strong>Administrator’s Insight</strong>: PSSO is the most important “Quality of Life” improvement for Mac management in 2026. It satisfies both the strict “Security Compliance” requirements of the education department and the “User Convenience” demands of the teaching staff.</p>\n",
          "important": false,
          "tags": [
            "Platform SSO",
            "Passwordless",
            "Security Standards",
            "MOE Requirements",
            "Authentication"
          ],
          "category": "Section 7: Advanced Mac Management"
        },
        {
          "id": "mac-26",
          "question": "Mixed Fleet Management: Using Smart Groups to distinguish between Intel and Apple Silicon software packages.",
          "answer": "<p><strong>2026 is the sunset year for Intel Macs. Most schools have a hybrid environment containing both ‘x86_64 (Intel)’ and ‘arm 64 (M1–M5)’ architectures. Assigning the wrong software package can lead to non-functional apps or system instability.</strong></p>\n<h2>I. Creating Precise Smart Groups (SOP)</h2>\n<p>IT coordinators should establish these baseline groups in Jamf Pro for accurate deployment:</p>\n<h3>1. Apple Silicon Group (Primary)</h3>\n<ul>\n<li><strong>Criteria</strong>: <code>Architecture Type</code></li>\n<li><strong>Operator</strong>: <code>is</code></li>\n<li><strong>Value</strong>: <code>arm 64</code> (or <code>Apple Silicon</code>)</li>\n</ul>\n<h3>2. Intel Mac Group (Legacy)</h3>\n<ul>\n<li><strong>Criteria</strong>: <code>Architecture Type</code></li>\n<li><strong>Operator</strong>: <code>is</code></li>\n<li><strong>Value</strong>: <code>x86_64</code></li>\n</ul>\n<h3>3. Rosetta 2 Status Group</h3>\n<ul>\n<li>Create a group for “Apple Silicon Macs MISSING Rosetta 2” to automatically trigger the installation of the Rosetta translation environment if you still rely on legacy Intel apps.</li>\n</ul>\n<h2>II. Recommended Deployment Strategy</h2>\n<ol>\n<li>\n<p><strong>Prioritize Universal Binaries</strong>: If a developer provides a Universal installer (e.g., Google Chrome or Microsoft Office), use it. macOS will automatically run the correct architecture.</p>\n</li>\n<li>\n<p><strong>Architecture-Specific .pkgs</strong>:</p>\n<ul>\n<li>For professional software (Adobe Creative Cloud, specialized lab tools), upload separate packages: <code>App_v1.0_AppleSilicon.pkg</code> and <code>App_v1.0_Intel.pkg</code>.</li>\n<li>Scope the former to the Apple Silicon group and the latter to the Intel group.</li>\n</ul>\n</li>\n<li>\n<p><strong>App Store Apps (VPP)</strong>: This is the most efficient method. Apple’s servers automatically detect the client architecture and download the optimized version. Use VPP whenever possible.</p>\n</li>\n</ol>\n<h2>III. Operational Advice</h2>\n<ul>\n<li><strong>System Updates</strong>: macOS 26 handles updates differently for each architecture. Always use <strong>Declarative Device Management (DDM)</strong> for OS updates; the system will autonomously verify and install the correct update files without manual intervention.</li>\n<li><strong>Asset Tagging</strong>: Add an “Expiring Support 2028” tag to your Intel Smart Group. This helps in visually tracking budget requirements for the final phase-out of the Intel fleet.</li>\n</ul>\n<p><strong>Administrator’s Insight</strong>: The key to managing a mixed environment is “precise grouping.” Once your Smart Groups are set, subsequent software deployment becomes error-proof, and it allows for a more scientific understanding of your school’s hardware health.</p>\n",
          "important": false,
          "tags": [
            "Hybrid Environment",
            "Intel Mac",
            "Apple Silicon",
            "Smart Group",
            "Deployment Strategy"
          ],
          "category": "Section 7: Advanced Mac Management"
        },
        {
          "id": "mac-27",
          "question": "Automated Maintenance: Using macOS 26 DDM for 'Smart Energy Management' (Eco-friendly vs. Scheduled Updates).",
          "answer": "<p><strong>In the past, school IT wanted computers ON for updates, while the facility manager wanted them OFF to save electricity. macOS 26 and DDM provide a perfect automated balance.</strong></p>\n<h2>I. DDM Power Configuration Strategy (SOP)</h2>\n<p>Using macOS 26 <strong>System Configurations</strong>, you can set the following intelligent logic:</p>\n<ol>\n<li>\n<p><strong>Dynamic Sleep Schedule</strong>:</p>\n<ul>\n<li><strong>School Hours</strong>: Set a 20-minute idle-to-sleep timer for immediate student access.</li>\n<li><strong>Night Mode</strong>: After 6:00 PM, transition to a deep sleep state (Power Nap).</li>\n</ul>\n</li>\n<li>\n<p><strong>Update-Initiated Wake</strong>:</p>\n<ul>\n<li><strong>Configuration</strong>: Enable <code>Allow Wake for Managed Activity</code> in the DDM payload.</li>\n<li><strong>Effect</strong>: Even if the Mac is asleep, when Jamf Pro pushes a <strong>Security Response (RSR)</strong> or a <strong>DDM Software Declaration</strong>, the Mac will briefly “wake,” complete the background installation, and return to deep sleep once the task is reported as successful.</li>\n</ul>\n</li>\n<li>\n<p><strong>Energy Auditing (Status Channel)</strong>:</p>\n<ul>\n<li>You can monitor “Battery Cycle Counts” or “Up-time in High Performance Mode” via the DDM Status Channel to use as quantitative data for future hardware replacement cycles.</li>\n</ul>\n</li>\n</ol>\n<h2>II. Operational Recommendations</h2>\n<ul>\n<li><strong>Avoid Hard Power Cuts</strong>: Discourage the facility team from cutting the main circuit to the lab at night. This prevents M4/M5 Macs from performing essential background maintenance tasks like AI indexing, Spotlight optimization, and system cache cleaning.</li>\n<li><strong>Nudge Integration</strong>: If an update requires a restart, use a <strong>Nudge</strong> notification to ask the teacher to “Restart Now” the next morning, rather than forcing a midnight reboot that could cause loss of unsaved teaching materials.</li>\n</ul>\n<h2>III. Real-World Case Study</h2>\n<p>A school with 100 M5 Mac minis configured a “2:00 AM Power Nap” DDM window. These machines check for updates and security patches nightly. The average electricity cost increase per machine was less than $0.20 per month, yet 100% of the fleet remained on the latest secure version without a single man-hour of IT labor.</p>\n<p><strong>Administrator’s Insight</strong>: Declaring your energy policy via DDM allows the library and labs to be “Smarter, not just off,” solving the long-standing conflict between IT maintenance and school energy savings.</p>\n",
          "important": false,
          "tags": [
            "Energy Policy",
            "DDM",
            "Auto-Update",
            "Power Management",
            "macOS 26"
          ],
          "category": "Section 7: Advanced Mac Management"
        },
        {
          "id": "mac-28",
          "question": "First-Aid: What to do if Mac Enrollment hangs after a 'Wipe All Content and Settings' (EACS) reset.",
          "answer": "<p><strong>While ‘Erase All Content and Settings (EACS)’ is highly stable, school environments with captive-portal Wi-Fi or strict firewalls can cause the Mac to hang at the ‘Remote Management’ enrollment screen.</strong></p>\n<h2>I. Initial Diagnosis: Why is it hanging?</h2>\n<ol>\n<li><strong>Time Sync (Most Common)</strong>: If the Mac’s system time differs significantly from the Apple servers, SSL certificate validation will fail.</li>\n<li><strong>Network Restrictions</strong>: The school Wi-Fi requires a certificate that hasn’t been deployed yet, or the firewall is blocking port 443 to <code>*apple.com</code>.</li>\n<li><strong>ASM Assignment</strong>: The serial number in Apple School Manager has not been properly assigned to the target MDM server.</li>\n</ol>\n<h2>II. Recovery Techniques (SOP)</h2>\n<h3>Technique 1: Force System Time Sync (Terminal)</h3>\n<p>At the Setup Assistant screen, press <strong>Command + Option + T</strong> to open the Terminal (or access it from the Utilities menu):</p>\n<pre><code class=\"language-bash\">\n# Sync with Apple's time server\n\nsntp -sS time.apple.com\n\n# OR set manually (Format: MMDDhhmmYY)\n\ndate 0115100026\n\n</code></pre>\n<h3>Technique 2: Manually Trigger the Cloud Query</h3>\n<p>Run the following command to force the Mac to ask Apple, “Who is my manager?”:</p>\n<pre><code class=\"language-bash\">\nsudo profiles renew -type enrollment\n\n</code></pre>\n<h3>Technique 3: The iPhone Hotspot Bypass</h3>\n<p>If the school firewall is the bottleneck, connect the Mac to an administrator’s <strong>iPhone Hotspot</strong>. This bypasses campus network restrictions and allows the small “Enrollment” packet to reach the server. Once the Mac reaches the desktop, the MDM policies will take over and switch the Wi-Fi back to the school network.</p>\n<h2>III. Advanced Offline Recovery</h2>\n<p>If EACS fails completely to trigger, enter <strong>Recovery Mode</strong>:</p>\n<ol>\n<li>\n<p><strong>Apple Silicon (M1–M5)</strong>: Hold the Power button until “Loading startup options” appears.</p>\n</li>\n<li>\n<p><strong>Intel Mac (T2)</strong>: Hold <code>Command + R</code> during startup.</p>\n</li>\n<li>\n<p><strong>Action</strong>: Select “Erase Mac” from the Recovery menu. This forces a complete reset of the Secure Enclave and all hardware-bound security keys, allowing for a fresh start.</p>\n</li>\n</ol>\n<p><strong>Administrator’s Insight</strong>: Don’t panic when a batch of Macs hangs during enrollment. 90% of failures are solved by simply “Syncing the Time” or “Changing the Hotspot.” We recommend IT leads keep a USB drive with a list of required Apple domains/ports to assist the networking team in troubleshooting.</p>\n",
          "important": true,
          "tags": [
            "EACS",
            "ADE Troubleshooting",
            "Network Auth",
            "Terminal Commands",
            "Recovery Mode"
          ],
          "category": "Section 7: Advanced Mac Management"
        },
        {
          "id": "mac-29",
          "question": "How to push system updates (iOS/iPadOS/macOS) via Jamf Pro?",
          "answer": "<p><strong>By 2026, software update management in Jamf Pro has fully transitioned to the “Declarative Device Management (DDM)” framework.</strong> This approach is more stable than legacy remote commands and allows devices to autonomously handle the download and installation process, significantly reducing server load.</p>\n<h2>1. Using “Software Update Blueprints”</h2>\n<p>This is the recommended and most professional method:</p>\n<ol>\n<li>\n<p>Navigate to <strong><code>Settings</code> &gt; <code>Device Management</code> &gt; <code>Software Update Blueprints</code></strong>.</p>\n</li>\n<li>\n<p>Click <code>New</code> and set the target version (e.g., iOS 26.x or macOS 26 Tahoe).</p>\n</li>\n<li>\n<p><strong>Key Setting: Enforcement Deadline</strong>:</p>\n<ul>\n<li>Set a specific date and time (e.g., Three days from now at 5:00 PM).</li>\n<li>Before the deadline, users will receive gentle system notifications.</li>\n<li><strong>Once the deadline is reached, the device will ignore the user’s state, force a restart, and install the update.</strong></li>\n</ul>\n</li>\n<li>\n<p>Assign this blueprint to the target device group.</p>\n</li>\n</ol>\n<h2>2. Using Mass Actions for Remote Commands (Legacy Way)</h2>\n<p>If you need to send an update immediately to a specific set of search results:</p>\n<ol>\n<li>\n<p>On the search results page for <code>Mobile Devices</code> or <code>Computers</code>, click <strong><code>Action</code></strong> at the bottom right.</p>\n</li>\n<li>\n<p>Choose <strong><code>Send Remote Commands</code></strong>.</p>\n</li>\n<li>\n<p>Select <strong>“Update OS version on supervised devices”</strong> from the list.</p>\n</li>\n<li>\n<p>On the <strong>“Update OS Options”</strong> page, choose your desired settings:</p>\n<ul>\n<li><strong>Target Version</strong>: Recommended to select “Latest version based on device eligibility.”</li>\n<li><strong>Action</strong>:\n<ul>\n<li><strong>Download the update for users to install</strong>: The device will pre-download the files, and students can install them at their convenience.</li>\n<li><strong>Download and install the update, and restart devices after installation</strong>: This forces the update immediately; ideal for scheduling after school hours.</li>\n</ul>\n</li>\n</ul>\n</li>\n</ol>\n<h2>3. Management Highlights for 2026: macOS 26 Tahoe and Intel Macs</h2>\n<ul>\n<li><strong>Legacy Support</strong>: macOS 26 is the final version to support Intel-based Macs. For these older devices, allow double the download time and ensure the <strong>Bootstrap Token</strong> is correctly escrowed.</li>\n<li><strong>DDM Autonomy</strong>: In the latest systems, devices use DDM declarations to automatically perform updates when connected to power and idle (e.g., overnight), with much higher success rates than traditional push commands.</li>\n</ul>\n<h2>Best Practices:</h2>\n<ol>\n<li><strong>Avoid Exam Weeks</strong>: While updates can be enforced, avoid doing so during exam periods or presentations to prevent devices from entering the 15–30 minute update screen unexpectedly.</li>\n<li><strong>Power Confirmation</strong>: Remind students to plug in their iPad/Mac overnight when an update is scheduled. Constant power is the most critical factor for a successful update.</li>\n</ol>\n",
          "important": true,
          "tags": [
            "System Updates",
            "Jamf Pro",
            "DDM",
            "Software Update Blueprints",
            "iOS Update",
            "macOS Update"
          ],
          "category": "Section 1: Hardware & OS Updates"
        }
      ]
    }
  ]
}
